cube_scramble_cli/__init__.py
cube_scramble_cli/__main__.py
cube_scramble_cli/stopwatch.py
cube_scramble_cli-0.4.7.dist-info/LICENSE
cube_scramble_cli-0.4.7.dist-info/METADATA
cube_scramble_cli-0.4.7.dist-info/WHEEL
cube_scramble_cli-0.4.7.dist-info/entry_points.txt
cube_scramble_cli-0.4.7.dist-info/top_level.txt
cube_scramble_cli-0.4.7.dist-info/RECORD
