Metadata-Version: 2.1
Name: cube-scramble-cli
Version: 0.4.7
Summary: A CLI for pyTwistyScrambler, to generate random states for Rubik's cubes/twisty puzzles.
Home-page: https://gitlab.com/seanbreckenridge/cube-scramble-cli
Author: Sean Breckenridge
Author-email: seanbrecke@gmail.com
License: MIT
Keywords: cube puzzle scramble rubiks
Platform: UNKNOWN
Classifier: Development Status :: 3 - Alpha
Classifier: Intended Audience :: End Users/Desktop
Classifier: License :: OSI Approved :: MIT License
Classifier: Natural Language :: English
Classifier: Programming Language :: Python :: 3.6
Classifier: Programming Language :: Python :: 3.7
Classifier: Programming Language :: Python :: 3.8
Requires-Dist: tabulate (>=0.7.4)
Requires-Dist: prompt-toolkit (>=2.0.8)
Requires-Dist: pyTwistyScrambler (>=1.2)
